Master_STT/__init__.py
Master_STT-0.1.dist-info/METADATA
Master_STT-0.1.dist-info/WHEEL
Master_STT-0.1.dist-info/top_level.txt
Master_STT-0.1.dist-info/RECORD
