Metadata-Version: 2.1
Name: Master-STT
Version: 0.1
Summary: This is the speech to text package created by shiva
Author: M.ShivaKumar
Author-email: mr.point.break5@gmail.com
